pytest_variant/__init__.py
pytest_variant/plugin.py
tests/__init__.py
tests/conftest.py
tests/test_filter.py
tests/test_helpers.py
tests/test_sources.py
pytest_variant-1.1.0.dist-info/LICENSE
pytest_variant-1.1.0.dist-info/METADATA
pytest_variant-1.1.0.dist-info/WHEEL
pytest_variant-1.1.0.dist-info/entry_points.txt
pytest_variant-1.1.0.dist-info/top_level.txt
pytest_variant-1.1.0.dist-info/RECORD
