Metadata-Version: 2.1
Name: pytest-variant
Version: 1.1.0
Summary: Variant support for Pytest
Home-page: https://github.com/c4deszes/pytest-variant
Author: Balazs Eszes
Author-email: c4deszes@gmail.com
License: MIT
Project-URL: Documentation, https://github.com/c4deszes/pytest-variant
Project-URL: Source Code, https://github.com/c4deszes/pytest-variant
Keywords: pytest,variant
Platform: UNKNOWN
Classifier: Framework :: Pytest
Classifier: License :: OSI Approved :: MIT License
Classifier: Operating System :: OS Independent
License-File: LICENSE
